drb/fuse/__init__.py
drb/fuse/_version.py
drb/fuse/drb_fuse3.py
drb_fuse-1.0.0.data/data/requirements.txt
drb_fuse-1.0.0.dist-info/METADATA
drb_fuse-1.0.0.dist-info/WHEEL
drb_fuse-1.0.0.dist-info/top_level.txt
drb_fuse-1.0.0.dist-info/RECORD
