Metadata-Version: 2.1
Name: drb-fuse
Version: 1.0.0
Summary: DRB fuse implementation
Home-page: https://git.gael.fr/gael10/drb/drb-python/drb_python_fuse
Author: GAEL Systems
Author-email: drb-python@gael.fr
License: UNKNOWN
Project-URL: Documentation, http://drb-python.gitlab.io/fuse
Project-URL: Source, https://gitlab.com/drb-python/fuse
Platform: UNKNOWN
Classifier: Programming Language :: Python :: 3.8
Classifier: License :: OSI Approved :: Apache Software License
Classifier: Operating System :: OS Independent
Requires-Python: >=3.8
Requires-Dist: drb (~=2.0.3)
Requires-Dist: pyfuse3 (==3.2.2)
Requires-Dist: trio (==0.22.0)
